collective.disclaimer-1.0b1-py2.7-nspkg.pth
collective/disclaimer/__init__.py
collective/disclaimer/config.py
collective/disclaimer/configure.zcml
collective/disclaimer/interfaces.py
collective/disclaimer/logger.py
collective/disclaimer/profiles.zcml
collective/disclaimer/setuphandlers.py
collective/disclaimer/testing.py
collective/disclaimer/Extensions/Install.py
collective/disclaimer/Extensions/__init__.py
collective/disclaimer/browser/__init__.py
collective/disclaimer/browser/configure.zcml
collective/disclaimer/browser/controlpanel.py
collective/disclaimer/browser/disclaimer.pt
collective/disclaimer/browser/static/disclaimer-icon.png
collective/disclaimer/browser/static/disclaimer.css
collective/disclaimer/locales/collective.disclaimer.pot
collective/disclaimer/locales/manual.pot
collective/disclaimer/locales/plone.pot
collective/disclaimer/locales/es/LC_MESSAGES/collective.disclaimer.po
collective/disclaimer/locales/es/LC_MESSAGES/plone.po
collective/disclaimer/locales/pt_BR/LC_MESSAGES/collective.disclaimer.po
collective/disclaimer/locales/pt_BR/LC_MESSAGES/collective.disclaimer.temp.po
collective/disclaimer/locales/pt_BR/LC_MESSAGES/plone.po
collective/disclaimer/profiles/default/browserlayer.xml
collective/disclaimer/profiles/default/controlpanel.xml
collective/disclaimer/profiles/default/metadata.xml
collective/disclaimer/profiles/default/registry.xml
collective/disclaimer/profiles/default/rolemap.xml
collective/disclaimer/profiles/uninstall/browserlayer.xml
collective/disclaimer/profiles/uninstall/controlpanel.xml
collective/disclaimer/profiles/uninstall/registry.xml
collective/disclaimer/tests/__init__.py
collective/disclaimer/tests/test_controlpanel.py
collective/disclaimer/tests/test_robot.py
collective/disclaimer/tests/test_setup.py
collective/disclaimer/tests/test_viewlet.py
collective.disclaimer-1.0b1.dist-info/DESCRIPTION.rst
collective.disclaimer-1.0b1.dist-info/METADATA
collective.disclaimer-1.0b1.dist-info/RECORD
collective.disclaimer-1.0b1.dist-info/WHEEL
collective.disclaimer-1.0b1.dist-info/entry_points.txt
collective.disclaimer-1.0b1.dist-info/metadata.json
collective.disclaimer-1.0b1.dist-info/namespace_packages.txt
collective.disclaimer-1.0b1.dist-info/top_level.txt
